README.rst
setup.py
parselx/__init__.py
parselx/process.py
parselx/selector.py
parselx/utils.py
parselx/x_filters.py
parselx/x_processors.py
parselx.egg-info/PKG-INFO
parselx.egg-info/SOURCES.txt
parselx.egg-info/dependency_links.txt
parselx.egg-info/requires.txt
parselx.egg-info/top_level.txt