Metadata-Version: 1.2
Name: parselx
Version: 0.0.4
Summary: Enhanced version of parsel, extracting data from HTML and XML using complex rules
Home-page: https://github.com/wooddance/parselx
Author: wooddance
Author-email: zireael.me@gmail.com
License: UNKNOWN
Platform: UNKNOWN
Requires-Python: >=3.6.0
